utility_package/__init__.py
utility_package/datamanipulation.py
easymanipulation-0.0.1.dist-info/LICENSE
easymanipulation-0.0.1.dist-info/METADATA
easymanipulation-0.0.1.dist-info/WHEEL
easymanipulation-0.0.1.dist-info/top_level.txt
easymanipulation-0.0.1.dist-info/RECORD
