Metadata-Version: 2.1
Name: easymanipulation
Version: 0.0.1
Summary: Utility functions for data manipulation in pandas
Home-page: https://github.com/scottabarnes/Data-Scientist-Nanodegree/tree/master/2-Software-Engineering
Author: Scott Barnes
Author-email: email@email.com
License: UNKNOWN
Platform: UNKNOWN
Classifier: Programming Language :: Python :: 3
Classifier: License :: OSI Approved :: MIT License
Classifier: Operating System :: OS Independent
Requires-Python: >=3.6
